yatte/__init__.py
yatte/cli.py
yatte/taskfile.py
yatte/tasklist.py
yatte/utils.py
yatte-0.10.0.dist-info/entry_points.txt
yatte-0.10.0.dist-info/LICENSE
yatte-0.10.0.dist-info/WHEEL
yatte-0.10.0.dist-info/METADATA
yatte-0.10.0.dist-info/RECORD
