Metadata-Version: 2.1
Name: yatte
Version: 0.10.0
Summary: A simple task runner
Author-email: JA Viljoen <javiljoen@javiljoen.net>
Requires-Python: ~=3.8
Classifier: Environment :: Console
Classifier: Topic :: Software Development :: Build Tools
Classifier: Topic :: Utilities
Requires-Dist: pytest ~= 7.2 ; extra == "test"
Project-URL: Documentation, https://yatte.javiljoen.net/
Project-URL: Source, https://git.sr.ht/~javiljoen/yatte/
Provides-Extra: test
